sshim/Server.py
sshim/__init__.py
sshim-1.3.3.dist-info/LICENSE
sshim-1.3.3.dist-info/METADATA
sshim-1.3.3.dist-info/WHEEL
sshim-1.3.3.dist-info/top_level.txt
sshim-1.3.3.dist-info/zip-safe
sshim-1.3.3.dist-info/RECORD
