Metadata-Version: 2.1
Name: sshim
Version: 1.3.3
Summary: Scriptable SSH server for testing SSH clients.
Home-page: http://www.engledew.com
Author: Simon Engledew
Author-email: simon@engledew.com
License: MIT
Keywords: ssh,paramiko,testing
Platform: UNKNOWN
Classifier: Development Status :: 1 - Planning
Classifier: Operating System :: OS Independent
Classifier: Programming Language :: Python
Requires-Dist: paramiko
Requires-Dist: six
Provides-Extra: tests
Requires-Dist: pytest ; extra == 'tests'
